flask_responser/__init__.py
flask_responser/models.py
flask_responser/utils.py
flask_responser-0.0.3a0.dist-info/METADATA
flask_responser-0.0.3a0.dist-info/WHEEL
flask_responser-0.0.3a0.dist-info/top_level.txt
flask_responser-0.0.3a0.dist-info/RECORD
