Metadata-Version: 2.2
Name: flask_responser
Version: 0.0.3a0
Summary: 一种新的方式来生成结构化的 JSON 响应，支持开发模式、自定义数据和消息，提升前后端交互的效率与一致性。
Author: alex_zhou
Author-email: alex@ycps.org.cn
Classifier: Programming Language :: Python :: 3
Classifier: License :: OSI Approved :: MIT License
Classifier: Operating System :: OS Independent
Requires-Python: >=3.7
Requires-Dist: flask
Dynamic: author
Dynamic: author-email
Dynamic: classifier
Dynamic: description
Dynamic: description-content-type
Dynamic: requires-dist
Dynamic: requires-python
Dynamic: summary
